k3stopwatch/__init__.py
k3stopwatch/k3stopwatch.py
k3stopwatch/synopsis.py
k3stopwatch-0.1.5.dist-info/licenses/LICENSE
k3stopwatch-0.1.5.dist-info/METADATA
k3stopwatch-0.1.5.dist-info/WHEEL
k3stopwatch-0.1.5.dist-info/top_level.txt
k3stopwatch-0.1.5.dist-info/RECORD
